nnea/__init__.py
nnea/logging_utils.py
nnea/config/__init__.py
nnea/config/defaults.py
nnea/config/settings.py
nnea/data_factory/__init__.py
nnea/data_factory/augmentation.py
nnea/data_factory/preprocessing.py
nnea/data_factory/rank.py
nnea/data_factory/validation.py
nnea/datasets/__init__.py
nnea/datasets/_download.py
nnea/io/__init__.py
nnea/io/_load.py
nnea/io/_nadata.py
nnea/io/_save.py
nnea/model/__init__.py
nnea/model/base.py
nnea/model/models.py
nnea/model/nnea_layers.py
nnea/model/nnea_model.py
nnea/plot/__init__.py
nnea/plot/basic.py
nnea/plot/explain_plots.py
nnea/plot/model_plots.py
nnea/utils/__init__.py
nnea/utils/helpers.py
nnea/utils/metrics.py
nnea-0.1.2.dist-info/licenses/LICENSE.txt
nnea_minimal/__init__.py
nnea_minimal/logging_utils.py
nnea_minimal/config/__init__.py
nnea_minimal/config/defaults.py
nnea_minimal/config/settings.py
nnea_minimal/io/__init__.py
nnea_minimal/io/_load.py
nnea_minimal/io/_nadata.py
nnea_minimal/model/__init__.py
nnea_minimal/model/base.py
nnea_minimal/model/models.py
nnea_minimal/utils/__init__.py
nnea_minimal/utils/helpers.py
nnea_minimal/utils/metrics.py
nnea-0.1.2.dist-info/METADATA
nnea-0.1.2.dist-info/WHEEL
nnea-0.1.2.dist-info/top_level.txt
nnea-0.1.2.dist-info/RECORD
